{
  "slug": "cloudnative",
  "name": "CloudNative",
  "published_at": "2026-01-25T16:06:29.239Z",
  "organizationCount": 1,
  "projectCount": 3,
  "years": [
    2022
  ],
  "organizations": [
    {
      "slug": "keptn",
      "name": "Keptn",
      "first_year": 2022,
      "last_year": 2022,
      "total_projects": 3,
      "is_currently_active": false,
      "active_years": [
        2022
      ]
    }
  ],
  "yearlyStats": {
    "2022": {
      "organizationCount": 1,
      "projectCount": 3
    }
  },
  "meta": {
    "version": 1,
    "generated_at": "2026-01-25T16:06:29.239Z"
  }
}